<annotation>
	<folder>JPEGImages（1）</folder>
	<filename>1461.jpg</filename>
	<path>C:\Users\a\Desktop\电脑文件\JPEGImages（1）\1461.jpg</path>
	<source>
		<database>Unknown</database>
	</source>
	<size>
		<width>500</width>
		<height>374</height>
		<depth>3</depth>
	</size>
	<segmented>0</segmented>
	<object>
		<name>face</name>
		<pose>Unspecified</pose>
		<truncated>1</truncated>
		<difficult>0</difficult>
		<bndbox>
			<xmin>204</xmin>
			<ymin>53</ymin>
			<xmax>500</xmax>
			<ymax>239</ymax>
		</bndbox>
	</object>
</annotation>
