<annotation>
	<folder>A3001-3500</folder>
	<filename>3152.jpg</filename>
	<path>D:\projects\A3001-3500\3152.jpg</path>
	<source>
		<database>Unknown</database>
	</source>
	<size>
		<width>300</width>
		<height>300</height>
		<depth>3</depth>
	</size>
	<segmented>0</segmented>
	<object>
		<name>face</name>
		<pose>Unspecified</pose>
		<truncated>0</truncated>
		<difficult>0</difficult>
		<bndbox>
			<xmin>120</xmin>
			<ymin>7</ymin>
			<xmax>288</xmax>
			<ymax>172</ymax>
		</bndbox>
	</object>
</annotation>
