<annotation>
	<folder>A5001-6000</folder>
	<filename>5065.jpg</filename>
	<path>D:\projects\A5001-6000\5065.jpg</path>
	<source>
		<database>Unknown</database>
	</source>
	<size>
		<width>500</width>
		<height>391</height>
		<depth>3</depth>
	</size>
	<segmented>0</segmented>
	<object>
		<name>face</name>
		<pose>Unspecified</pose>
		<truncated>0</truncated>
		<difficult>0</difficult>
		<bndbox>
			<xmin>60</xmin>
			<ymin>15</ymin>
			<xmax>184</xmax>
			<ymax>188</ymax>
		</bndbox>
	</object>
</annotation>
