<annotation>
	<folder>A8001-10000</folder>
	<filename>10140.jpg</filename>
	<path>D:\projects\A8001-10000\10140.jpg</path>
	<source>
		<database>Unknown</database>
	</source>
	<size>
		<width>400</width>
		<height>564</height>
		<depth>3</depth>
	</size>
	<segmented>0</segmented>
	<object>
		<name>face</name>
		<pose>Unspecified</pose>
		<truncated>0</truncated>
		<difficult>0</difficult>
		<bndbox>
			<xmin>144</xmin>
			<ymin>62</ymin>
			<xmax>323</xmax>
			<ymax>201</ymax>
		</bndbox>
	</object>
</annotation>
