<annotation>
	<folder>JPEGImages（1）</folder>
	<filename>768.jpg</filename>
	<path>C:\Users\a\Desktop\电脑文件\JPEGImages（1）\768.jpg</path>
	<source>
		<database>Unknown</database>
	</source>
	<size>
		<width>392</width>
		<height>500</height>
		<depth>3</depth>
	</size>
	<segmented>0</segmented>
	<object>
		<name>face</name>
		<pose>Unspecified</pose>
		<truncated>0</truncated>
		<difficult>0</difficult>
		<bndbox>
			<xmin>67</xmin>
			<ymin>32</ymin>
			<xmax>366</xmax>
			<ymax>334</ymax>
		</bndbox>
	</object>
</annotation>
