<annotation>
	<folder>JPEGImages（1）</folder>
	<filename>988.jpg</filename>
	<path>C:\Users\a\Desktop\电脑文件\JPEGImages（1）\988.jpg</path>
	<source>
		<database>Unknown</database>
	</source>
	<size>
		<width>265</width>
		<height>263</height>
		<depth>3</depth>
	</size>
	<segmented>0</segmented>
	<object>
		<name>face</name>
		<pose>Unspecified</pose>
		<truncated>0</truncated>
		<difficult>0</difficult>
		<bndbox>
			<xmin>14</xmin>
			<ymin>18</ymin>
			<xmax>261</xmax>
			<ymax>229</ymax>
		</bndbox>
	</object>
</annotation>
