<annotation>
	<folder>A7001-8000</folder>
	<filename>7271.jpg</filename>
	<path>D:\projects\A7001-8000\7271.jpg</path>
	<source>
		<database>Unknown</database>
	</source>
	<size>
		<width>500</width>
		<height>379</height>
		<depth>3</depth>
	</size>
	<segmented>0</segmented>
	<object>
		<name>face</name>
		<pose>Unspecified</pose>
		<truncated>0</truncated>
		<difficult>0</difficult>
		<bndbox>
			<xmin>105</xmin>
			<ymin>55</ymin>
			<xmax>288</xmax>
			<ymax>219</ymax>
		</bndbox>
	</object>
</annotation>
